odoo/addons/purchase_quick/README.rst
odoo/addons/purchase_quick/__init__.py
odoo/addons/purchase_quick/__manifest__.py
odoo/addons/purchase_quick/i18n/fr.po
odoo/addons/purchase_quick/i18n/purchase_quick.pot
odoo/addons/purchase_quick/models/__init__.py
odoo/addons/purchase_quick/models/product_product.py
odoo/addons/purchase_quick/models/purchase_order.py
odoo/addons/purchase_quick/readme/CONTRIBUTORS.rst
odoo/addons/purchase_quick/readme/DESCRIPTION.rst
odoo/addons/purchase_quick/readme/ROADMAP.rst
odoo/addons/purchase_quick/readme/USAGE.rst
odoo/addons/purchase_quick/static/description/filter.png
odoo/addons/purchase_quick/static/description/icon.png
odoo/addons/purchase_quick/static/description/index.html
odoo/addons/purchase_quick/static/description/po-product.png
odoo/addons/purchase_quick/static/description/po.png
odoo/addons/purchase_quick/tests/__init__.py
odoo/addons/purchase_quick/tests/test_quick_purchase.py
odoo/addons/purchase_quick/views/product_view.xml
odoo/addons/purchase_quick/views/purchase_view.xml
odoo12_addon_purchase_quick-12.0.1.0.3.dist-info/METADATA
odoo12_addon_purchase_quick-12.0.1.0.3.dist-info/WHEEL
odoo12_addon_purchase_quick-12.0.1.0.3.dist-info/top_level.txt
odoo12_addon_purchase_quick-12.0.1.0.3.dist-info/RECORD
